pyfancyplot/__init__.py
pyfancyplot/example_plots.py
pyfancyplot/plot.py
pyfancyplot/test.py
pyfancyplot/test_violin.py
pyfancyplots-0.1.dist-info/LICENSE
pyfancyplots-0.1.dist-info/METADATA
pyfancyplots-0.1.dist-info/WHEEL
pyfancyplots-0.1.dist-info/top_level.txt
pyfancyplots-0.1.dist-info/RECORD
