Metadata-Version: 2.1
Name: pyfancyplots
Version: 0.1
Summary: A python plotting script containing Luke Olson's styling preferences
Home-page: https://github.com/bienz2/PyFancyPlots
Author: Amanda Bienz
Author-email: bienz2@illinois.edu
License: UNKNOWN
Platform: UNKNOWN
Classifier: Programming Language :: Python :: 3
Classifier: License :: OSI Approved :: MIT License
Classifier: Operating System :: OS Independent
